vexo/__init__.py
vexo/cli.py
vexo/downloader.py
vexo/service.py
vexo/utils.py
vexo-2025.12.34.dist-info/licenses/LICENSE
vexo_for_bots/vexo/__init__.py
vexo_for_bots/vexo/cli.py
vexo_for_bots/vexo/downloader.py
vexo_for_bots/vexo/service.py
vexo_for_bots/vexo/utils.py
vexo-2025.12.34.dist-info/METADATA
vexo-2025.12.34.dist-info/WHEEL
vexo-2025.12.34.dist-info/entry_points.txt
vexo-2025.12.34.dist-info/top_level.txt
vexo-2025.12.34.dist-info/RECORD
