Metadata-Version: 2.4
Name: vexo
Version: 2025.12.34
Summary: The simplest YouTube downloader (CLI + Python API)
Home-page: https://github.com/vexo-team/vexo
Author: Vexo Team
Author-email: Vexo Team <contact@vexo.dev>
License: MIT
Project-URL: Homepage, https://github.com/vexo-team/vexo
Project-URL: Repository, https://github.com/vexo-team/vexo
Project-URL: Bug Tracker, https://github.com/vexo-team/vexo/issues
Classifier: Development Status :: 5 - Production/Stable
Classifier: Intended Audience :: Developers
Classifier: License :: OSI Approved :: MIT License
Classifier: Operating System :: OS Independent
Classifier: Programming Language :: Python :: 3
Classifier: Programming Language :: Python :: 3.8
Classifier: Programming Language :: Python :: 3.9
Classifier: Programming Language :: Python :: 3.10
Classifier: Programming Language :: Python :: 3.11
Classifier: Programming Language :: Python :: 3.12
Classifier: Topic :: Multimedia :: Video
Classifier: Topic :: Software Development :: Libraries :: Python Modules
Requires-Python: >=3.8
License-File: LICENSE
Requires-Dist: yt-dlp>=2023.12.30
Dynamic: author
Dynamic: home-page
Dynamic: license-file
Dynamic: requires-python
